jputils/Game.py
jputils-0.0.1.dist-info/METADATA
jputils-0.0.1.dist-info/WHEEL
jputils-0.0.1.dist-info/top_level.txt
jputils-0.0.1.dist-info/RECORD
