Metadata-Version: 2.1
Name: jputils
Version: 0.0.1
Summary: util modules by Jade
Home-page: https://github.com/indiflex/jputils
Author: Jade IndiFlex
Author-email: indiflex.corp@gmail.com
License: MIT
Platform: UNKNOWN
Requires-Dist: requests
